pandasai_docker/Dockerfile
pandasai_docker/__init__.py
pandasai_docker/docker_sandbox.py
pandasai_docker/serializer.py
pandasai_docker-0.1.4.dist-info/METADATA
pandasai_docker-0.1.4.dist-info/WHEEL
pandasai_docker-0.1.4.dist-info/RECORD
